signal_analyzer/__init__.py
signal_analyzer/main.py
signal_analyzer-1.1.3.dist-info/LICENCE
signal_analyzer-1.1.3.dist-info/METADATA
signal_analyzer-1.1.3.dist-info/WHEEL
signal_analyzer-1.1.3.dist-info/top_level.txt
signal_analyzer-1.1.3.dist-info/RECORD
