Metadata-Version: 2.1
Name: signal-analyzer
Version: 1.1.3
Summary: Agelient Signal Analyzer RF test module
Author-email: Ravi Maru <ravimaru20@icloud.com>
Classifier: Programming Language :: Python :: 3
Classifier: License :: OSI Approved :: MIT License
Classifier: Operating System :: OS Independent
Requires-Python: >=3.5
License-File: LICENCE
